pinyinCopybook/__init__.py
pinyinCopybook/font.py
pinyinCopybook/template.py
pinyinCopybook/fonts/Kaiti.ttf
pinyinCopybook/fonts/PinYin.ttf
pinyinCopybook/fonts/TYZKai.ttf
pinyinCopybook/fonts/simfang.ttf
pinyinCopybook-0.2.dist-info/LICENSE
pinyinCopybook-0.2.dist-info/METADATA
pinyinCopybook-0.2.dist-info/WHEEL
pinyinCopybook-0.2.dist-info/top_level.txt
pinyinCopybook-0.2.dist-info/RECORD
