Metadata-Version: 2.1
Name: pinyinCopybook
Version: 0.2
Summary: 拼音汉字田字格A4模版, 排版后生成Pillow Image
Author-email: Mike Song <gnosoir@hotmail.com>
License: Apache License
Project-URL: Homepage, https://github.com/mikesongming/PinyinCopybook
Project-URL: Issues, https://github.com/mikesongming/PinyinCopybook/issues
Keywords: pinyin,copybook
Classifier: License :: OSI Approved :: Apache Software License
Classifier: Development Status :: 3 - Alpha
Classifier: Programming Language :: Python :: 3
Classifier: Topic :: Text Processing :: Markup :: reStructuredText
Requires-Python: >=3.8
License-File: LICENSE
Requires-Dist: Pillow >=9.4.0
Requires-Dist: numpy >=1.24
Provides-Extra: dev
Requires-Dist: autopep8 ; extra == 'dev'
Requires-Dist: pytest ; extra == 'dev'
